README.md
setup.py
torcj/__init__.py
torcj/main.py
torcj/storage.json
torcj.egg-info/PKG-INFO
torcj.egg-info/SOURCES.txt
torcj.egg-info/dependency_links.txt
torcj.egg-info/top_level.txt