Metadata-Version: 2.1
Name: torcj
Version: 0.0.7
Summary: An example package
Author: Example
